nonebot_plugin_sanae/__init__.py
nonebot_plugin_sanae/config.py
nonebot_plugin_sanae-0.0.9.dist-info/METADATA
nonebot_plugin_sanae-0.0.9.dist-info/WHEEL
nonebot_plugin_sanae-0.0.9.dist-info/RECORD
