Metadata-Version: 2.1
Name: nonebot-plugin-sanae
Version: 0.0.9
Summary: sanae connecter
Home-page: https://github.com/Hoshinonyaruko/nonebot-plugin-sanae
License: MIT
Author: Hoshinonyaruko
Author-email: applegm@me.com
Requires-Python: >=3.8,<4.0
Classifier: License :: OSI Approved :: MIT License
Classifier: Programming Language :: Python :: 3
Classifier: Programming Language :: Python :: 3.8
Classifier: Programming Language :: Python :: 3.9
Classifier: Programming Language :: Python :: 3.10
Classifier: Programming Language :: Python :: 3.11
Requires-Dist: aiohttp (>=3.8.1,<4.0.0)
Requires-Dist: nonebot-adapter-onebot (>=2.1.5,<3.0.0)
Requires-Dist: nonebot2 (>=2.0.0-rc.1,<3.0.0)
Project-URL: Repository, https://github.com/Hoshinonyaruko/nonebot-plugin-sanae
